Metadata-Version: 2.1
Name: teree
Version: 0.1.1
Summary: Terminal tree -- package to print any objects as tree
Home-page: https://github.com/fagcinsk/teree
Author: Mikhail Yudin
Author-email: fagci.nsk@gmail.com
License: MIT
Keywords: terminal,tree,any object
Platform: UNKNOWN
Classifier: Development Status :: 3 - Alpha
Classifier: Intended Audience :: Developers
Classifier: Topic :: Software Development :: Build Tools
Classifier: License :: OSI Approved :: MIT License
Classifier: Programming Language :: Python :: 3
Classifier: Programming Language :: Python :: 3.4
Classifier: Programming Language :: Python :: 3.5
Classifier: Programming Language :: Python :: 3.6
